setup.py
kibana_logger/__init__.py
kibana_logger.egg-info/PKG-INFO
kibana_logger.egg-info/SOURCES.txt
kibana_logger.egg-info/dependency_links.txt
kibana_logger.egg-info/top_level.txt