Metadata-Version: 1.1
Name: kibana-logger
Version: 0.1.1
Summary: module to simply log in syslog with CEE/json format for analysing by kibana
Home-page: https://github.com/allan-simon/python-kibana-logger
Author: Allan SIMON
Author-email: allan.simon@supinfo.com
License: MIT
Keywords: kibana,syslog,cee,json
Platform: UNKNOWN
Classifier: Programming Language :: Python
Classifier: Development Status :: 4 - Beta
Classifier: Intended Audience :: Developers
Classifier: Operating System :: OS Independent
Classifier: Programming Language :: Python
Classifier: Topic :: Internet :: WWW/HTTP
